bdms/__init__.py
bdms-2.5.9001.dist-info/LICENSE
bdms-2.5.9001.dist-info/METADATA
bdms-2.5.9001.dist-info/WHEEL
bdms-2.5.9001.dist-info/top_level.txt
bdms-2.5.9001.dist-info/RECORD
