Metadata-Version: 2.1
Name: bdms
Version: 2.5.9001
Summary: bdms
Home-page: https://github.com/jaschilz/bdms/
Author: Joseph Schilz
Author-email: joseph@schilz.org
License: none
Platform: UNKNOWN
Classifier: Environment :: Web Environment
Classifier: Intended Audience :: Developers
Classifier: Operating System :: OS Independent
Classifier: Programming Language :: Python
Classifier: Programming Language :: Python :: 3.7
Classifier: Topic :: Internet :: WWW/HTTP
Classifier: Topic :: Internet :: WWW/HTTP :: Dynamic Content
